{
  "version": 1,
  "bugs": [
    {
      "id": "bug-001",
      "timestamp": "2026-06-27T09:16:33.805Z",
      "error_message": "Significant refactor of ",
      "file": "demo-web/index.html",
      "root_cause": "4 lines replaced/restructured",
      "fix": "Rewrote 23→32 lines (4 removed)",
      "tags": [
        "auto-detected",
        "refactor",
        "html"
      ],
      "related_bugs": [],
      "occurrences": 1,
      "last_seen": "2026-06-27T09:16:33.805Z"
    },
    {
      "id": "bug-002",
      "timestamp": "2026-06-27T09:35:45.290Z",
      "error_message": "Missing error handling in unknown",
      "file": "demo-web/index.html",
      "root_cause": "Code path had no error handling — exceptions would propagate uncaught",
      "fix": "Added try/catch block",
      "tags": [
        "auto-detected",
        "error-handling",
        "html"
      ],
      "related_bugs": [],
      "occurrences": 1,
      "last_seen": "2026-06-27T09:35:45.290Z"
    },
    {
      "id": "bug-003",
      "timestamp": "2026-06-27T09:53:35.697Z",
      "error_message": "Missing error handling in function",
      "file": "demo-web/index.html",
      "root_cause": "Code path had no error handling — exceptions would propagate uncaught",
      "fix": "Added try/catch block",
      "tags": [
        "auto-detected",
        "error-handling",
        "html"
      ],
      "related_bugs": [],
      "occurrences": 1,
      "last_seen": "2026-06-27T09:53:35.697Z"
    },
    {
      "id": "bug-004",
      "timestamp": "2026-06-27T10:18:43.139Z",
      "error_message": "Significant refactor of ",
      "file": "demo-web/index.html",
      "root_cause": "5 lines replaced/restructured",
      "fix": "Rewrote 13→6 lines (5 removed)",
      "tags": [
        "auto-detected",
        "refactor",
        "html"
      ],
      "related_bugs": [],
      "occurrences": 1,
      "last_seen": "2026-06-27T10:18:43.139Z"
    },
    {
      "id": "bug-005",
      "timestamp": "2026-06-27T10:20:21.283Z",
      "error_message": "Missing error handling in unknown",
      "file": "demo-web/index.html",
      "root_cause": "Code path had no error handling — exceptions would propagate uncaught",
      "fix": "Added try/catch block",
      "tags": [
        "auto-detected",
        "error-handling",
        "html"
      ],
      "related_bugs": [],
      "occurrences": 1,
      "last_seen": "2026-06-27T10:20:21.283Z"
    }
  ]
}